yaribak/__init__.py
yaribak/backup_processor.py
yaribak/human_interval.py
yaribak/main.py
yaribak/metadata.py
yaribak/utils.py
yaribak-0.0.6.dist-info/LICENSE
yaribak-0.0.6.dist-info/METADATA
yaribak-0.0.6.dist-info/WHEEL
yaribak-0.0.6.dist-info/entry_points.txt
yaribak-0.0.6.dist-info/top_level.txt
yaribak-0.0.6.dist-info/RECORD
