Metadata-Version: 2.1
Name: yaribak
Version: 0.0.6
Summary: Yet another rsync incremental backup utility
Home-page: https://github.com/hirak99/yaribak
Author: "Arnab Bose"
Author-email: hirak99+yaribak@gmail.com
Project-URL: Bug Tracker, https://github.com/hirak99/yaribak/issues
Classifier: Programming Language :: Python :: 3
Classifier: License :: OSI Approved :: MIT License
Classifier: Operating System :: OS Independent
Requires-Python: >=3.6
License-File: LICENSE
